README.rst
setup.py
ced/__init__.py
ced/ced
ced.egg-info/PKG-INFO
ced.egg-info/SOURCES.txt
ced.egg-info/dependency_links.txt
ced.egg-info/entry_points.txt
ced.egg-info/top_level.txt