Metadata-Version: 1.1
Name: ced
Version: 0.1
Summary: A lightweight, cross-platform, no-dependency configuration editor.
Home-page: https://github.com/regisb/ced
Author: Régis Behmo
Author-email: nospam@behmo.com
License: MIT
Platform: UNKNOWN
Classifier: Programming Language :: Python
Classifier: Programming Language :: Python :: 2.7
Classifier: Programming Language :: Python :: 3.3
Classifier: Programming Language :: Python :: 3.4
Classifier: Programming Language :: Python :: 3.5
